[
  {
    "player": "warror230",
    "rank": "Duke",
    "x": -12891,
    "z": -3219,
    "originalTimestamp": 1768760438815
  },
  {
    "player": "Awkward28",
    "rank": "Noble",
    "x": 9873,
    "z": -3110,
    "originalTimestamp": 1768760438815
  },
  {
    "player": "Brod547",
    "rank": "Explorer",
    "x": -21323,
    "z": 9906,
    "originalTimestamp": 1768760438815
  },
  {
    "player": "NeutralGaming",
    "rank": "Archduke",
    "x": -12739,
    "z": -4066,
    "originalTimestamp": 1768760438815
  },
  {
    "player": "FPSMaster157885",
    "rank": "Member",
    "x": 8397,
    "z": 5942,
    "originalTimestamp": 1768760438815
  },
  {
    "player": "djmaximovich",
    "rank": "Duke",
    "x": 6798,
    "z": -4705,
    "originalTimestamp": 1768760438815
  },
  {
    "player": "Ssoorreis",
    "rank": "Supporter",
    "x": -357,
    "z": -6596,
    "originalTimestamp": 1768760438815
  },
  {
    "player": "EVILMedusa",
    "rank": "Supporter",
    "x": -559,
    "z": -6654,
    "originalTimestamp": 1768760438815
  },
  {
    "player": "o_v_0",
    "rank": "Colonist",
    "x": -5509,
    "z": -7274,
    "originalTimestamp": 1768760438815
  },
  {
    "player": "dxnketa",
    "rank": "Viceroy",
    "x": -12755,
    "z": -4050,
    "originalTimestamp": 1768760438815
  },
  {
    "player": "Yaros_Jarro",
    "rank": "Member",
    "x": 3943,
    "z": 355,
    "originalTimestamp": 1768760438815
  },
  {
    "player": "BlueQPH",
    "rank": "Colonist",
    "x": 9899,
    "z": -3114,
    "originalTimestamp": 1768760438815
  },
  {
    "player": "AmericaPlacer",
    "rank": "Duke",
    "x": -12751,
    "z": -4060,
    "originalTimestamp": 1768760438815
  },
  {
    "player": "CrystalMagician",
    "rank": "Supporter",
    "x": 12274,
    "z": -8046,
    "originalTimestamp": 1768760438815
  },
  {
    "player": "evr3nk",
    "rank": "Supporter",
    "x": -12755,
    "z": -4066,
    "originalTimestamp": 1768760438815
  },
  {
    "player": "9bright",
    "rank": "Excelsior",
    "x": 6797,
    "z": -4698,
    "originalTimestamp": 1768760438815
  },
  {
    "player": "SCRDGLITCH",
    "rank": "Member",
    "x": 7351,
    "z": -3063,
    "originalTimestamp": 1768760438815
  },
  {
    "player": "QuickNam",
    "rank": "Member",
    "x": -12807,
    "z": -3738,
    "originalTimestamp": 1768760438815
  },
  {
    "player": "Error",
    "rank": "Duke",
    "x": -12741,
    "z": -4084,
    "originalTimestamp": 1768760438815
  },
  {
    "player": "baddawg333",
    "rank": "Colonist",
    "x": 6804,
    "z": -4690,
    "originalTimestamp": 1768760438815
  },
  {
    "player": "farastanpatriot9",
    "rank": "Supporter",
    "x": -12748,
    "z": -4064,
    "originalTimestamp": 1768760438815
  },
  {
    "player": "FarastanPatriot2",
    "rank": "Supporter",
    "x": -12801,
    "z": -3747,
    "originalTimestamp": 1768760438815
  },
  {
    "player": "Afferzan",
    "rank": "Duke",
    "x": -20710,
    "z": 9836,
    "originalTimestamp": 1768760438815
  },
  {
    "player": "Twoerr",
    "rank": "Conquistador",
    "x": -12742,
    "z": -4074,
    "originalTimestamp": 1768760438815
  },
  {
    "player": "FarastanChampion",
    "rank": "Voter",
    "x": 7375,
    "z": -3036,
    "originalTimestamp": 1768760438815
  },
  {
    "player": "Davifrancis",
    "rank": "Helper",
    "x": 16138,
    "z": 1482,
    "originalTimestamp": 1768760438815
  },
  {
    "player": "fomnano23451",
    "rank": "Noble",
    "x": 6802,
    "z": -4698,
    "originalTimestamp": 1768760438815
  },
  {
    "player": "PandaMagician",
    "rank": "Excelsior",
    "x": -12803,
    "z": -3736,
    "originalTimestamp": 1768760438815
  },
  {
    "player": "AlchakSigma",
    "rank": "Duke",
    "x": 6798,
    "z": -4698,
    "originalTimestamp": 1768760438815
  },
  {
    "player": "ElAurens",
    "rank": "Conquistador",
    "x": -12759,
    "z": -4051,
    "originalTimestamp": 1768760438815
  },
  {
    "player": "lionoflegio",
    "rank": "Duke",
    "x": -12748,
    "z": -4066,
    "originalTimestamp": 1768760438815
  },
  {
    "player": "NetherWraithh",
    "rank": "Voyager",
    "x": 6793,
    "z": -4701,
    "originalTimestamp": 1768760438815
  },
  {
    "player": "Tuve",
    "rank": "Supporter",
    "x": -12739,
    "z": -4084,
    "originalTimestamp": 1768760438815
  },
  {
    "player": "NyaaaIdTrap",
    "rank": "Excelsior",
    "x": -12802,
    "z": -3725,
    "originalTimestamp": 1768760438815
  },
  {
    "player": "Geo",
    "rank": "Duke",
    "x": -314,
    "z": -6592,
    "originalTimestamp": 1768760438815
  },
  {
    "player": "vCrust",
    "rank": "Colonist",
    "x": -12745,
    "z": -4066,
    "originalTimestamp": 1768760438815
  },
  {
    "player": "GreenlandicChamp",
    "rank": "Duke",
    "x": -6434,
    "z": -8093,
    "originalTimestamp": 1768760438815
  },
  {
    "player": "Contt",
    "rank": "Excelsior",
    "x": -12755,
    "z": -4067,
    "originalTimestamp": 1768760438815
  },
  {
    "player": "Xyrothic",
    "rank": "Conquistador",
    "x": 13672,
    "z": 3194,
    "originalTimestamp": 1768760438815
  },
  {
    "player": "evilgsouxi",
    "rank": "Supporter",
    "x": 16518,
    "z": 1965,
    "originalTimestamp": 1768760438815
  },
  {
    "player": "Psychodeine",
    "rank": "Member",
    "x": 661,
    "z": -737,
    "originalTimestamp": 1768760438815
  },
  {
    "player": "BritishAteriko",
    "rank": "Supporter",
    "x": 5,
    "z": -6390,
    "originalTimestamp": 1768760438815
  },
  {
    "player": "Urs34ever",
    "rank": "Noble",
    "x": -257,
    "z": -6566,
    "originalTimestamp": 1768760438815
  },
  {
    "player": "Jc499",
    "rank": "Conquistador",
    "x": -8787,
    "z": 5067,
    "originalTimestamp": 1768760438815
  },
  {
    "player": "TrapQueenSeth",
    "rank": "Duke",
    "x": 6801,
    "z": -4707,
    "originalTimestamp": 1768760438815
  },
  {
    "player": "Piicklles",
    "rank": "Excelsior",
    "x": 15873,
    "z": 898,
    "originalTimestamp": 1768760438815
  },
  {
    "player": "DiscoSpider",
    "rank": "Supporter",
    "x": -19387,
    "z": -7948,
    "originalTimestamp": 1768760438815
  },
  {
    "player": "ApexTaco",
    "rank": "Conquistador",
    "x": -12744,
    "z": -4045,
    "originalTimestamp": 1768760438815
  },
  {
    "player": "FaceyZino",
    "rank": "Duke",
    "x": 17077,
    "z": 1012,
    "originalTimestamp": 1768760438815
  },
  {
    "player": "TNTistheplace4me",
    "rank": "Viceroy",
    "x": -14856,
    "z": -4934,
    "originalTimestamp": 1768760438815
  },
  {
    "player": "fanafane",
    "rank": "Supporter",
    "x": -12743,
    "z": -4060,
    "originalTimestamp": 1768760438815
  }
]