[
  {
    "player": "Ace_Kit",
    "rank": "Voyager",
    "x": 9942,
    "z": -2667,
    "originalTimestamp": 1768915999370
  },
  {
    "player": "Jc499",
    "rank": "Conquistador",
    "x": -8822,
    "z": 5074,
    "originalTimestamp": 1768915999370
  },
  {
    "player": "Tuve",
    "rank": "Supporter",
    "x": 2430,
    "z": -5131,
    "originalTimestamp": 1768915999370
  },
  {
    "player": "Stepan01",
    "rank": "Voyager",
    "x": 7040,
    "z": -2432,
    "originalTimestamp": 1768915999370
  }
]