[
  {
    "player": "Locktia",
    "rank": "Supporter",
    "x": 7843,
    "z": -6112,
    "originalTimestamp": 1768316497664
  },
  {
    "player": "PRUSSIAN_JAGER",
    "rank": "Member",
    "x": 16839,
    "z": -7062,
    "originalTimestamp": 1768316497664
  },
  {
    "player": "ALiteralFlower",
    "rank": "Explorer",
    "x": 17045,
    "z": -7152,
    "originalTimestamp": 1768316497664
  },
  {
    "player": "OGTorta",
    "rank": "Excelsior",
    "x": -1750,
    "z": -2992,
    "originalTimestamp": 1768316497664
  },
  {
    "player": "Minshka",
    "rank": "Colonist",
    "x": 16823,
    "z": -4442,
    "originalTimestamp": 1768316497664
  },
  {
    "player": "RatRaceRobot",
    "rank": "Member",
    "x": -2800,
    "z": -1907,
    "originalTimestamp": 1768316497664
  },
  {
    "player": "Crewette_PL",
    "rank": "Noble",
    "x": 2862,
    "z": 3132,
    "originalTimestamp": 1768316497664
  },
  {
    "player": "Joshi2x3",
    "rank": "Member",
    "x": 4509,
    "z": -7630,
    "originalTimestamp": 1768316497664
  },
  {
    "player": "zakry2024",
    "rank": "Voyager",
    "x": -11262,
    "z": -3966,
    "originalTimestamp": 1768316497664
  },
  {
    "player": "Commendo",
    "rank": "Viceroy",
    "x": 11254,
    "z": -7774,
    "originalTimestamp": 1768316497664
  }
]