[
  {
    "player": "Yeat",
    "rank": "Duke",
    "x": 5685,
    "z": 2615,
    "originalTimestamp": 1768823223208
  },
  {
    "player": "o_v_0",
    "rank": "Colonist",
    "x": -5515,
    "z": -7268,
    "originalTimestamp": 1768823223208
  },
  {
    "player": "Ricola4325",
    "rank": "Excelsior",
    "x": 5361,
    "z": 2699,
    "originalTimestamp": 1768823223208
  },
  {
    "player": "Gray",
    "rank": "Supporter",
    "x": 13695,
    "z": 2866,
    "originalTimestamp": 1768823223208
  },
  {
    "player": "TheForgottenGreg",
    "rank": "Voyager",
    "x": 17148,
    "z": -6164,
    "originalTimestamp": 1768823223208
  },
  {
    "player": "NK_Grimm",
    "rank": "Member",
    "x": 14877,
    "z": -1382,
    "originalTimestamp": 1768823223208
  },
  {
    "player": "Xiyler",
    "rank": "Conquistador",
    "x": -2408,
    "z": -7905,
    "originalTimestamp": 1768823223208
  },
  {
    "player": "matt",
    "rank": "Supporter",
    "x": -3736,
    "z": -4767,
    "originalTimestamp": 1768823223208
  },
  {
    "player": "Yaros_Jarro",
    "rank": "Member",
    "x": 3941,
    "z": 359,
    "originalTimestamp": 1768823223208
  },
  {
    "player": "Nija2die",
    "rank": "Conquistador",
    "x": 18218,
    "z": 3891,
    "originalTimestamp": 1768823223208
  },
  {
    "player": "Rehent_",
    "rank": "Member",
    "x": 3942,
    "z": 359,
    "originalTimestamp": 1768823223208
  },
  {
    "player": "J4EB_by_Nem0s",
    "rank": "Explorer",
    "x": 3011,
    "z": 2962,
    "originalTimestamp": 1768823223208
  }
]