[
  {
    "player": "PRUSSIAN_JAGER",
    "rank": "Member",
    "x": 16698,
    "z": -6489,
    "originalTimestamp": 1768396360197
  },
  {
    "player": "Seb7lafrite",
    "rank": "Voyager",
    "x": 16149,
    "z": -909,
    "originalTimestamp": 1768396360197
  },
  {
    "player": "olexandrooo",
    "rank": "Member",
    "x": -10377,
    "z": -4441,
    "originalTimestamp": 1768396360197
  },
  {
    "player": "Itsleon0909",
    "rank": "Excelsior",
    "x": 8290,
    "z": -5224,
    "originalTimestamp": 1768396360197
  },
  {
    "player": "kinsukghoshXD",
    "rank": "Noble",
    "x": 20275,
    "z": 5524,
    "originalTimestamp": 1768396360197
  }
]