[
  {
    "player": "Jestorius",
    "rank": "Colonist",
    "x": 16900,
    "z": -7043,
    "originalTimestamp": 1766518294380
  },
  {
    "player": "gsouxi",
    "rank": "Supporter",
    "x": 1098,
    "z": -5972,
    "originalTimestamp": 1766518294380
  },
  {
    "player": "Saumya",
    "rank": "Supporter",
    "x": 7615,
    "z": -8411,
    "originalTimestamp": 1766518294380
  },
  {
    "player": "OrigamiWawa",
    "rank": "Voter",
    "x": 11377,
    "z": -9645,
    "originalTimestamp": 1766518294380
  },
  {
    "player": "starstruckfate",
    "rank": "Viceroy",
    "x": 9214,
    "z": -1110,
    "originalTimestamp": 1766518294380
  },
  {
    "player": "maroonspinodino",
    "rank": "Member",
    "x": -10738,
    "z": -5550,
    "originalTimestamp": 1766518294380
  },
  {
    "player": "bbplayer79",
    "rank": "Member",
    "x": -10427,
    "z": -6274,
    "originalTimestamp": 1766518294380
  },
  {
    "player": "HeroAI9",
    "rank": "Member",
    "x": 15335,
    "z": -45,
    "originalTimestamp": 1766518294380
  },
  {
    "player": "ZMJ56",
    "rank": "Voyager",
    "x": 13211,
    "z": -7800,
    "originalTimestamp": 1766518294380
  },
  {
    "player": "DaHoodedBoss",
    "rank": "Noble",
    "x": 15720,
    "z": 2559,
    "originalTimestamp": 1766518294380
  },
  {
    "player": "asoooery",
    "rank": "Voyager",
    "x": -7267,
    "z": 3158,
    "originalTimestamp": 1766518294380
  },
  {
    "player": "TheGrayMagician",
    "rank": "Viceroy",
    "x": 15800,
    "z": 2597,
    "originalTimestamp": 1766518294380
  },
  {
    "player": "Urs34ever",
    "rank": "Noble",
    "x": -334,
    "z": -6564,
    "originalTimestamp": 1766518294380
  },
  {
    "player": "Foxfire3321",
    "rank": "Noble",
    "x": -11083,
    "z": -5745,
    "originalTimestamp": 1766518294380
  },
  {
    "player": "JustAA_0",
    "rank": "Member",
    "x": -2818,
    "z": -1827,
    "originalTimestamp": 1766518294380
  },
  {
    "player": "The_Mechanic",
    "rank": "Supporter",
    "x": -18411,
    "z": -8043,
    "originalTimestamp": 1766518294380
  },
  {
    "player": "Davi",
    "rank": "Helper",
    "x": 16137,
    "z": 1623,
    "originalTimestamp": 1766518294380
  },
  {
    "player": "stonelord567",
    "rank": "Voyager",
    "x": 3065,
    "z": 4074,
    "originalTimestamp": 1766518294380
  },
  {
    "player": "Ikeelyou7",
    "rank": "Noble",
    "x": -11557,
    "z": -3829,
    "originalTimestamp": 1766518294380
  },
  {
    "player": "evr67nk",
    "rank": "Supporter",
    "x": 207,
    "z": -5804,
    "originalTimestamp": 1766518294380
  },
  {
    "player": "Hamicus",
    "rank": "Explorer",
    "x": -4811,
    "z": 628,
    "originalTimestamp": 1766518294380
  },
  {
    "player": "Locktia",
    "rank": "Supporter",
    "x": 7443,
    "z": -7713,
    "originalTimestamp": 1766518294380
  },
  {
    "player": "Brod547",
    "rank": "Voter",
    "x": 10000,
    "z": -3045,
    "originalTimestamp": 1766518294380
  },
  {
    "player": "ZaneKnight",
    "rank": "Member",
    "x": -1047,
    "z": -6189,
    "originalTimestamp": 1766518294380
  },
  {
    "player": "ItsleonO9O9O9O9",
    "rank": "Excelsior",
    "x": 11423,
    "z": -7542,
    "originalTimestamp": 1766518294380
  },
  {
    "player": "Unsunglampblep",
    "rank": "Explorer",
    "x": -10154,
    "z": -6321,
    "originalTimestamp": 1766518294380
  },
  {
    "player": "PolishDestroyer",
    "rank": "Supporter",
    "x": 3594,
    "z": 3777,
    "originalTimestamp": 1766518294380
  },
  {
    "player": "djwall23",
    "rank": "Explorer",
    "x": -19144,
    "z": -6701,
    "originalTimestamp": 1766518294380
  },
  {
    "player": "Makuferis",
    "rank": "Supporter",
    "x": -9139,
    "z": 246,
    "originalTimestamp": 1766518294380
  },
  {
    "player": "Bluenextcrystal",
    "rank": "Viceroy",
    "x": 12272,
    "z": -8148,
    "originalTimestamp": 1766518294380
  },
  {
    "player": "Geo",
    "rank": "Duke",
    "x": -345,
    "z": -6884,
    "originalTimestamp": 1766518294380
  }
]