[
  {
    "player": "Jestorius",
    "rank": "Conquistador",
    "x": 17204,
    "z": -7896,
    "originalTimestamp": 1769031946202
  },
  {
    "player": "Rovoiyan",
    "rank": "Member",
    "x": 17223,
    "z": -8204,
    "originalTimestamp": 1769031946202
  },
  {
    "player": "Palmelia",
    "rank": "Noble",
    "x": 13617,
    "z": 2941,
    "originalTimestamp": 1769031946202
  },
  {
    "player": "Itz_iber",
    "rank": "Voyager",
    "x": -10135,
    "z": -5677,
    "originalTimestamp": 1769031946202
  },
  {
    "player": "Dimashqi",
    "rank": "Supporter",
    "x": 4667,
    "z": -4120,
    "originalTimestamp": 1769031946202
  },
  {
    "player": "Noobstar9998",
    "rank": "Member",
    "x": 16926,
    "z": -7623,
    "originalTimestamp": 1769031946202
  },
  {
    "player": "SimonOnkaas",
    "rank": "Member",
    "x": 14077,
    "z": -3614,
    "originalTimestamp": 1769031946202
  },
  {
    "player": "Danyel5151ed",
    "rank": "Noble",
    "x": -7376,
    "z": 4321,
    "originalTimestamp": 1769031946202
  },
  {
    "player": "Schwere_mom",
    "rank": "Viceroy",
    "x": 1137,
    "z": -5736,
    "originalTimestamp": 1769031946202
  },
  {
    "player": "Jc499",
    "rank": "Conquistador",
    "x": -8780,
    "z": 4882,
    "originalTimestamp": 1769031946202
  },
  {
    "player": "Weronz",
    "rank": "Explorer",
    "x": 4663,
    "z": -4121,
    "originalTimestamp": 1769031946202
  },
  {
    "player": "thedripkingg",
    "rank": "Viceroy",
    "x": -1540,
    "z": -2675,
    "originalTimestamp": 1769031946202
  },
  {
    "player": "ALiteralFlower",
    "rank": "Colonist",
    "x": 17234,
    "z": -8229,
    "originalTimestamp": 1769031946202
  },
  {
    "player": "Sniperlbaron",
    "rank": "Conquistador",
    "x": 16838,
    "z": -7601,
    "originalTimestamp": 1769031946202
  },
  {
    "player": "Anonymus_Player",
    "rank": "Duke",
    "x": 1119,
    "z": -5738,
    "originalTimestamp": 1769031946202
  },
  {
    "player": "AJDoesMC_07",
    "rank": "Viceroy",
    "x": 13989,
    "z": 3937,
    "originalTimestamp": 1769031946202
  },
  {
    "player": "Canadian_Hawk",
    "rank": "Voyager",
    "x": 1488,
    "z": 1857,
    "originalTimestamp": 1769031946202
  },
  {
    "player": "Fuchs",
    "rank": "Supporter",
    "x": -1197,
    "z": -714,
    "originalTimestamp": 1769031946202
  },
  {
    "player": "njminerock",
    "rank": "Member",
    "x": 7120,
    "z": -3891,
    "originalTimestamp": 1769031946202
  },
  {
    "player": "NyaaaIdPrep",
    "rank": "Excelsior",
    "x": 6913,
    "z": -3869,
    "originalTimestamp": 1769031946202
  },
  {
    "player": "NewGenNinja",
    "rank": "Viceroy",
    "x": -18371,
    "z": -7828,
    "originalTimestamp": 1769031946202
  },
  {
    "player": "Criss_cloudy",
    "rank": "Helper",
    "x": 16285,
    "z": 1815,
    "originalTimestamp": 1769031946202
  },
  {
    "player": "whistlehill05",
    "rank": "Explorer",
    "x": 7612,
    "z": -3061,
    "originalTimestamp": 1769031946202
  },
  {
    "player": "cristianzr",
    "rank": "Voyager",
    "x": -8783,
    "z": 4889,
    "originalTimestamp": 1769031946202
  },
  {
    "player": "DarthDilly",
    "rank": "Member",
    "x": -19392,
    "z": -7063,
    "originalTimestamp": 1769031946202
  }
]