[
  {
    "player": "PRUSSIAN_JAGER",
    "rank": "Member",
    "x": 12208,
    "z": -9348,
    "originalTimestamp": 1767805287240
  },
  {
    "player": "OGBunlik",
    "rank": "Excelsior",
    "x": -1496,
    "z": -993,
    "originalTimestamp": 1767805287240
  },
  {
    "player": "Nija2die",
    "rank": "Colonist",
    "x": 18244,
    "z": 3987,
    "originalTimestamp": 1767805287240
  },
  {
    "player": "TheWatiRed98",
    "rank": "Member",
    "x": -16649,
    "z": 1255,
    "originalTimestamp": 1767805287240
  },
  {
    "player": "deathtoworlds",
    "rank": "Explorer",
    "x": 20276,
    "z": 5525,
    "originalTimestamp": 1767805287240
  },
  {
    "player": "soodspoun",
    "rank": "Viceroy",
    "x": 14335,
    "z": -560,
    "originalTimestamp": 1767805287240
  },
  {
    "player": "NeutralGaming",
    "rank": "Duke",
    "x": 18270,
    "z": 3965,
    "originalTimestamp": 1767805287240
  },
  {
    "player": "DaHoodedBoss",
    "rank": "Noble",
    "x": 18263,
    "z": 3836,
    "originalTimestamp": 1767805287240
  },
  {
    "player": "Weronz",
    "rank": "Explorer",
    "x": 4939,
    "z": -4106,
    "originalTimestamp": 1767805287240
  },
  {
    "player": "Ronkula10",
    "rank": "Noble",
    "x": 6551,
    "z": -1483,
    "originalTimestamp": 1767805287240
  },
  {
    "player": "Leothecat2009",
    "rank": "Viceroy",
    "x": 2411,
    "z": -5666,
    "originalTimestamp": 1767805287240
  },
  {
    "player": "orsetto109",
    "rank": "Explorer",
    "x": -14723,
    "z": -4549,
    "originalTimestamp": 1767805287240
  },
  {
    "player": "MedvedSRB",
    "rank": "Member",
    "x": 4923,
    "z": -4114,
    "originalTimestamp": 1767805287240
  },
  {
    "player": "AlShami",
    "rank": "Supporter",
    "x": 4927,
    "z": -4118,
    "originalTimestamp": 1767805287240
  },
  {
    "player": "Medusa",
    "rank": "Supporter",
    "x": 14503,
    "z": 250,
    "originalTimestamp": 1767805287240
  },
  {
    "player": "hzyoda_",
    "rank": "Excelsior",
    "x": 14504,
    "z": 244,
    "originalTimestamp": 1767805287240
  },
  {
    "player": "evr3nk",
    "rank": "Supporter",
    "x": 528,
    "z": -5535,
    "originalTimestamp": 1767805287240
  },
  {
    "player": "gsouxi",
    "rank": "Supporter",
    "x": 14498,
    "z": 244,
    "originalTimestamp": 1767805287240
  },
  {
    "player": "PhilipG_",
    "rank": "Explorer",
    "x": -2817,
    "z": -1811,
    "originalTimestamp": 1767805287240
  },
  {
    "player": "inocent",
    "rank": "Viceroy",
    "x": 9755,
    "z": -2652,
    "originalTimestamp": 1767805287240
  }
]