[
  {
    "player": "Itz_iber",
    "rank": "Explorer",
    "x": -9960,
    "z": -5211,
    "originalTimestamp": 1769369552441
  },
  {
    "player": "XZeLoXX",
    "rank": "Explorer",
    "x": 14078,
    "z": -3611,
    "originalTimestamp": 1769369552441
  },
  {
    "player": "Jeremy",
    "rank": "Excelsior",
    "x": 2229,
    "z": 3568,
    "originalTimestamp": 1769369552441
  },
  {
    "player": "ALiteralFlower",
    "rank": "Colonist",
    "x": 17228,
    "z": -8223,
    "originalTimestamp": 1769369552441
  },
  {
    "player": "dvon816",
    "rank": "Supporter",
    "x": 5648,
    "z": -5253,
    "originalTimestamp": 1769369552441
  },
  {
    "player": "Jc499",
    "rank": "Conquistador",
    "x": -8786,
    "z": 5078,
    "originalTimestamp": 1769369552441
  },
  {
    "player": "Camper",
    "rank": "Supporter",
    "x": -10009,
    "z": -1834,
    "originalTimestamp": 1769369552441
  },
  {
    "player": "OH3L4",
    "rank": "Colonist",
    "x": 6087,
    "z": -1161,
    "originalTimestamp": 1769369552441
  },
  {
    "player": "v3ect0r",
    "rank": "Explorer",
    "x": 17096,
    "z": -6523,
    "originalTimestamp": 1769369552441
  },
  {
    "player": "OSMPG",
    "rank": "Member",
    "x": 6067,
    "z": -1106,
    "originalTimestamp": 1769369552441
  },
  {
    "player": "SimonOnkaas",
    "rank": "Voyager",
    "x": 14065,
    "z": -3641,
    "originalTimestamp": 1769369552441
  },
  {
    "player": "Teksas",
    "rank": "Archduke",
    "x": -11651,
    "z": -3952,
    "originalTimestamp": 1769369552441
  },
  {
    "player": "ElAurens",
    "rank": "Conquistador",
    "x": 2698,
    "z": -3942,
    "originalTimestamp": 1769369552441
  },
  {
    "player": "SkyWolf",
    "rank": "Excelsior",
    "x": 2730,
    "z": -4011,
    "originalTimestamp": 1769369552441
  },
  {
    "player": "Jarnogfc",
    "rank": "Conquistador",
    "x": 5498,
    "z": 2921,
    "originalTimestamp": 1769369552441
  },
  {
    "player": "CosmicKangShrmpi",
    "rank": "Supporter",
    "x": 2716,
    "z": -3913,
    "originalTimestamp": 1769369552441
  },
  {
    "player": "Contt",
    "rank": "Excelsior",
    "x": 2793,
    "z": -3880,
    "originalTimestamp": 1769369552441
  },
  {
    "player": "pkty",
    "rank": "Viceroy",
    "x": -11349,
    "z": -4007,
    "originalTimestamp": 1769369552441
  },
  {
    "player": "TNTistheplace4me",
    "rank": "Viceroy",
    "x": -7385,
    "z": -1948,
    "originalTimestamp": 1769369552441
  },
  {
    "player": "zazaman060",
    "rank": "Member",
    "x": 3015,
    "z": -1345,
    "originalTimestamp": 1769369552441
  },
  {
    "player": "Gurtthebuilder",
    "rank": "Supporter",
    "x": 13224,
    "z": 810,
    "originalTimestamp": 1769369552441
  },
  {
    "player": "CunningCommander",
    "rank": "Member",
    "x": 17231,
    "z": -8224,
    "originalTimestamp": 1769369552441
  },
  {
    "player": "PeacefulBuilder",
    "rank": "Supporter",
    "x": -7864,
    "z": -5818,
    "originalTimestamp": 1769369552441
  },
  {
    "player": "BopBop",
    "rank": "Duke",
    "x": 2706,
    "z": -4070,
    "originalTimestamp": 1769369552441
  },
  {
    "player": "BGamer1704",
    "rank": "Colonist",
    "x": 2907,
    "z": -3883,
    "originalTimestamp": 1769369552441
  },
  {
    "player": "Micheal__Bank",
    "rank": "Excelsior",
    "x": -8165,
    "z": -7451,
    "originalTimestamp": 1769369552441
  },
  {
    "player": "evr3nk",
    "rank": "Supporter",
    "x": 2707,
    "z": -4070,
    "originalTimestamp": 1769369552441
  },
  {
    "player": "Guanine",
    "rank": "Duke",
    "x": 2675,
    "z": -4070,
    "originalTimestamp": 1769369552441
  },
  {
    "player": "beppo56",
    "rank": "Explorer",
    "x": 12311,
    "z": 306,
    "originalTimestamp": 1769369552441
  },
  {
    "player": "Davi",
    "rank": "Helper",
    "x": -15499,
    "z": -7966,
    "originalTimestamp": 1769369552441
  },
  {
    "player": "CaptainTaias44",
    "rank": "Voyager",
    "x": 4436,
    "z": 2681,
    "originalTimestamp": 1769369552441
  },
  {
    "player": "starstruckfate",
    "rank": "Supporter",
    "x": -241,
    "z": -200,
    "originalTimestamp": 1769369552441
  },
  {
    "player": "chigglesYT",
    "rank": "Conquistador",
    "x": -19282,
    "z": -7340,
    "originalTimestamp": 1769369552441
  },
  {
    "player": "987898",
    "rank": "Voyager",
    "x": -5095,
    "z": 422,
    "originalTimestamp": 1769369552441
  },
  {
    "player": "SzaWbiee",
    "rank": "Archduke",
    "x": -351,
    "z": -5066,
    "originalTimestamp": 1769369552441
  },
  {
    "player": "meinte",
    "rank": "Supporter",
    "x": 15467,
    "z": 2647,
    "originalTimestamp": 1769369552441
  },
  {
    "player": "TheWatiRed98",
    "rank": "Explorer",
    "x": 19742,
    "z": 5446,
    "originalTimestamp": 1769369552441
  },
  {
    "player": "VisualParsley38",
    "rank": "Noble",
    "x": 4696,
    "z": 1915,
    "originalTimestamp": 1769369552441
  },
  {
    "player": "zakry2024",
    "rank": "Voyager",
    "x": -11906,
    "z": -3739,
    "originalTimestamp": 1769369552441
  },
  {
    "player": "Op229179_",
    "rank": "Member",
    "x": 5489,
    "z": 2825,
    "originalTimestamp": 1769369552441
  },
  {
    "player": "Funmasterr",
    "rank": "Viceroy",
    "x": 3143,
    "z": -7887,
    "originalTimestamp": 1769369552441
  },
  {
    "player": "LongtheBist",
    "rank": "Viceroy",
    "x": 4956,
    "z": -5313,
    "originalTimestamp": 1769369552441
  }
]