[
  {
    "player": "TrashXClips",
    "rank": "Explorer",
    "x": 13005,
    "z": -1299,
    "originalTimestamp": 1767333114946
  },
  {
    "player": "starstruckfate",
    "rank": "Supporter",
    "x": -11189,
    "z": -5730,
    "originalTimestamp": 1767333114946
  },
  {
    "player": "BoomTheSeaLion",
    "rank": "Supporter",
    "x": -14622,
    "z": -4736,
    "originalTimestamp": 1767333114946
  },
  {
    "player": "RussianTycoon",
    "rank": "Excelsior",
    "x": 11562,
    "z": -4022,
    "originalTimestamp": 1767333114946
  },
  {
    "player": "OrigamiWawa",
    "rank": "Duke",
    "x": 9882,
    "z": -2899,
    "originalTimestamp": 1767333114946
  },
  {
    "player": "tekcrawlz",
    "rank": "Archduke",
    "x": -11635,
    "z": -3952,
    "originalTimestamp": 1767333114946
  },
  {
    "player": "o_v_0",
    "rank": "Colonist",
    "x": -5323,
    "z": -7229,
    "originalTimestamp": 1767333114946
  },
  {
    "player": "gigantos_bruh",
    "rank": "Conquistador",
    "x": -11661,
    "z": -3995,
    "originalTimestamp": 1767333114946
  },
  {
    "player": "KongoBearH",
    "rank": "Archduke",
    "x": 1518,
    "z": 1862,
    "originalTimestamp": 1767333114946
  },
  {
    "player": "Vanaco_Defender7",
    "rank": "Supporter",
    "x": 2500,
    "z": -16,
    "originalTimestamp": 1767333114946
  },
  {
    "player": "sanky1109",
    "rank": "Noble",
    "x": 15193,
    "z": -3969,
    "originalTimestamp": 1767333114946
  },
  {
    "player": "Dpro65",
    "rank": "Member",
    "x": -11633,
    "z": -3954,
    "originalTimestamp": 1767333114946
  },
  {
    "player": "Nayakk",
    "rank": "Voyager",
    "x": 8045,
    "z": -6003,
    "originalTimestamp": 1767333114946
  },
  {
    "player": "ACE",
    "rank": "Supporter",
    "x": -8728,
    "z": 4799,
    "originalTimestamp": 1767333114946
  },
  {
    "player": "szepess",
    "rank": "Conquistador",
    "x": 12491,
    "z": -9418,
    "originalTimestamp": 1767333114946
  }
]