[
  {
    "player": "OGConcord4Life",
    "rank": "Supporter",
    "x": -14866,
    "z": -6302,
    "originalTimestamp": 1768196046857
  },
  {
    "player": "9dj2",
    "rank": "Explorer",
    "x": -11566,
    "z": -3832,
    "originalTimestamp": 1768196046857
  },
  {
    "player": "MeridianHydra",
    "rank": "Supporter",
    "x": 7718,
    "z": -6225,
    "originalTimestamp": 1768196046857
  },
  {
    "player": "crimsonghost0909",
    "rank": "Colonist",
    "x": 3474,
    "z": -7764,
    "originalTimestamp": 1768196046857
  }
]