[
  {
    "player": "squeaky_possum",
    "rank": "Conquistador",
    "x": 4604,
    "z": -6949,
    "originalTimestamp": 1769616281915
  },
  {
    "player": "evr3nk",
    "rank": "Supporter",
    "x": 88,
    "z": -5604,
    "originalTimestamp": 1769616281915
  },
  {
    "player": "Scath_Maru",
    "rank": "Member",
    "x": 17080,
    "z": -8340,
    "originalTimestamp": 1769616281915
  },
  {
    "player": "Davi",
    "rank": "Helper",
    "x": -15535,
    "z": -7966,
    "originalTimestamp": 1769616281915
  },
  {
    "player": "Pigylord",
    "rank": "Excelsior",
    "x": 16802,
    "z": -4252,
    "originalTimestamp": 1769616281915
  },
  {
    "player": "Rometheus",
    "rank": "Excelsior",
    "x": 351,
    "z": -1996,
    "originalTimestamp": 1769616281915
  },
  {
    "player": "CrystalMagician",
    "rank": "Supporter",
    "x": 12144,
    "z": -8185,
    "originalTimestamp": 1769616281915
  },
  {
    "player": "Locktia",
    "rank": "Supporter",
    "x": 8992,
    "z": -6669,
    "originalTimestamp": 1769616281915
  },
  {
    "player": "Radioactive661",
    "rank": "Voyager",
    "x": 17105,
    "z": -8246,
    "originalTimestamp": 1769616281915
  },
  {
    "player": "MatiCooolGuy",
    "rank": "Member",
    "x": 13980,
    "z": -3614,
    "originalTimestamp": 1769616281915
  },
  {
    "player": "PeacefulBuilder",
    "rank": "Supporter",
    "x": -7879,
    "z": -6586,
    "originalTimestamp": 1769616281915
  },
  {
    "player": "GhostBuddyOnTop",
    "rank": "Member",
    "x": 5720,
    "z": 2447,
    "originalTimestamp": 1769616281915
  },
  {
    "player": "Mey45",
    "rank": "Viceroy",
    "x": 2505,
    "z": 1155,
    "originalTimestamp": 1769616281915
  },
  {
    "player": "dvon816",
    "rank": "Supporter",
    "x": 5598,
    "z": -5243,
    "originalTimestamp": 1769616281915
  },
  {
    "player": "Geo",
    "rank": "Duke",
    "x": -360,
    "z": -6598,
    "originalTimestamp": 1769616281915
  },
  {
    "player": "FosterZillaH3X",
    "rank": "Supporter",
    "x": 16967,
    "z": -4722,
    "originalTimestamp": 1769616281915
  },
  {
    "player": "zuma88",
    "rank": "Viceroy",
    "x": 13580,
    "z": -309,
    "originalTimestamp": 1769616281915
  },
  {
    "player": "waqst",
    "rank": "Excelsior",
    "x": -17,
    "z": -5526,
    "originalTimestamp": 1769616281915
  }
]