[
  {
    "player": "Korubin",
    "rank": "Supporter",
    "x": 3679,
    "z": -4767,
    "originalTimestamp": 1768161727449
  },
  {
    "player": "Heers66",
    "rank": "Viceroy",
    "x": -1665,
    "z": -1249,
    "originalTimestamp": 1768161727449
  },
  {
    "player": "ilovemyfemboys",
    "rank": "Noble",
    "x": 16016,
    "z": 1559,
    "originalTimestamp": 1768161727449
  },
  {
    "player": "VisualParsley38",
    "rank": "Noble",
    "x": -14650,
    "z": -4732,
    "originalTimestamp": 1768161727449
  },
  {
    "player": "Brod547",
    "rank": "Explorer",
    "x": 10307,
    "z": -3136,
    "originalTimestamp": 1768161727449
  },
  {
    "player": "DuckyZach",
    "rank": "Supporter",
    "x": 10319,
    "z": -3138,
    "originalTimestamp": 1768161727449
  },
  {
    "player": "Makuferis",
    "rank": "Supporter",
    "x": -9021,
    "z": 83,
    "originalTimestamp": 1768161727449
  },
  {
    "player": "OrigamiWawa",
    "rank": "Duke",
    "x": 11394,
    "z": -9663,
    "originalTimestamp": 1768161727449
  },
  {
    "player": "orsetto109",
    "rank": "Explorer",
    "x": -14737,
    "z": -4561,
    "originalTimestamp": 1768161727449
  },
  {
    "player": "Yoru27",
    "rank": "Member",
    "x": 13924,
    "z": -3938,
    "originalTimestamp": 1768161727449
  },
  {
    "player": "Afferzan",
    "rank": "Viceroy",
    "x": 10039,
    "z": -3098,
    "originalTimestamp": 1768161727449
  },
  {
    "player": "Dimashqi",
    "rank": "Member",
    "x": 4648,
    "z": -4123,
    "originalTimestamp": 1768161727449
  },
  {
    "player": "Weronz",
    "rank": "Explorer",
    "x": 4644,
    "z": -4102,
    "originalTimestamp": 1768161727449
  },
  {
    "player": "sheepgodthe1",
    "rank": "Member",
    "x": -11795,
    "z": -2957,
    "originalTimestamp": 1768161727449
  },
  {
    "player": "Nf_miracle",
    "rank": "Member",
    "x": 14000,
    "z": -4061,
    "originalTimestamp": 1768161727449
  },
  {
    "player": "Khashiii",
    "rank": "Member",
    "x": 14189,
    "z": -4028,
    "originalTimestamp": 1768161727449
  },
  {
    "player": "Tendonkeys",
    "rank": "Member",
    "x": 13897,
    "z": -3865,
    "originalTimestamp": 1768161727449
  },
  {
    "player": "sleaps",
    "rank": "Conquistador",
    "x": -145,
    "z": -7251,
    "originalTimestamp": 1768161727449
  },
  {
    "player": "HonkDooder",
    "rank": "Member",
    "x": 14187,
    "z": -4024,
    "originalTimestamp": 1768161727449
  },
  {
    "player": "raftrelict",
    "rank": "Member",
    "x": 4639,
    "z": -4284,
    "originalTimestamp": 1768161727449
  },
  {
    "player": "recon927",
    "rank": "Supporter",
    "x": -7860,
    "z": -7674,
    "originalTimestamp": 1768161727449
  },
  {
    "player": "BlockWorks123",
    "rank": "Viceroy",
    "x": -146,
    "z": -7250,
    "originalTimestamp": 1768161727449
  },
  {
    "player": "ALiteralFlower",
    "rank": "Explorer",
    "x": 17091,
    "z": -7269,
    "originalTimestamp": 1768161727449
  },
  {
    "player": "Illyt",
    "rank": "Explorer",
    "x": -162,
    "z": -7220,
    "originalTimestamp": 1768161727449
  },
  {
    "player": "Blue_Catfish",
    "rank": "Voyager",
    "x": 296,
    "z": -5019,
    "originalTimestamp": 1768161727449
  },
  {
    "player": "itechniker",
    "rank": "Explorer",
    "x": 17000,
    "z": -7174,
    "originalTimestamp": 1768161727449
  },
  {
    "player": "Medusa",
    "rank": "Supporter",
    "x": 14145,
    "z": -4711,
    "originalTimestamp": 1768161727449
  },
  {
    "player": "Kokomo309",
    "rank": "Member",
    "x": 13828,
    "z": -4002,
    "originalTimestamp": 1768161727449
  },
  {
    "player": "Davi",
    "rank": "Helper",
    "x": 16170,
    "z": 1721,
    "originalTimestamp": 1768161727449
  },
  {
    "player": "ace22890",
    "rank": "Member",
    "x": -8324,
    "z": 6008,
    "originalTimestamp": 1768161727449
  },
  {
    "player": "OGConcord4Life",
    "rank": "Supporter",
    "x": -14297,
    "z": -4255,
    "originalTimestamp": 1768161727449
  },
  {
    "player": "WHYGUY0327",
    "rank": "Member",
    "x": -12216,
    "z": -5939,
    "originalTimestamp": 1768161727449
  }
]