[
  {
    "player": "Ikaria_Locktia",
    "rank": "Supporter",
    "x": 7936,
    "z": -5476,
    "originalTimestamp": 1765572221458
  },
  {
    "player": "Dvrk_Dvce",
    "rank": "Colonist",
    "x": 13491,
    "z": -4467,
    "originalTimestamp": 1765572221458
  },
  {
    "player": "Zakazel",
    "rank": "Colonist",
    "x": -10935,
    "z": 27,
    "originalTimestamp": 1765572221458
  },
  {
    "player": "JDanielsito",
    "rank": "Voyager",
    "x": -8678,
    "z": 4360,
    "originalTimestamp": 1765572221458
  },
  {
    "player": "Meridian_Patriot",
    "rank": "Supporter",
    "x": 9749,
    "z": -3115,
    "originalTimestamp": 1765572221458
  },
  {
    "player": "BritishAteriko",
    "rank": "Supporter",
    "x": 66,
    "z": -6253,
    "originalTimestamp": 1765572221458
  },
  {
    "player": "TheWorldRequiem",
    "rank": "Colonist",
    "x": 16634,
    "z": 1937,
    "originalTimestamp": 1765572221458
  },
  {
    "player": "BritishDuck",
    "rank": "Archduke",
    "x": 74,
    "z": -6256,
    "originalTimestamp": 1765572221458
  },
  {
    "player": "Chuar",
    "rank": "Voyager",
    "x": -8532,
    "z": 3882,
    "originalTimestamp": 1765572221458
  },
  {
    "player": "2kwa_",
    "rank": "Archduke",
    "x": -2490,
    "z": -7709,
    "originalTimestamp": 1765572221458
  },
  {
    "player": "Marivelle",
    "rank": "Duke",
    "x": 16623,
    "z": 1937,
    "originalTimestamp": 1765572221458
  },
  {
    "player": "Strawkiti",
    "rank": "Voyager",
    "x": -8550,
    "z": 3905,
    "originalTimestamp": 1765572221458
  },
  {
    "player": "Makuferis",
    "rank": "Supporter",
    "x": -9223,
    "z": -343,
    "originalTimestamp": 1765572221458
  },
  {
    "player": "SchruteFarms327",
    "rank": "Viceroy",
    "x": 7159,
    "z": -3107,
    "originalTimestamp": 1765572221458
  },
  {
    "player": "orsetto109",
    "rank": "Member",
    "x": -14440,
    "z": -4143,
    "originalTimestamp": 1765572221458
  },
  {
    "player": "bob_jake_ish",
    "rank": "Noble",
    "x": -6078,
    "z": 2558,
    "originalTimestamp": 1765572221458
  },
  {
    "player": "Vikkuling",
    "rank": "Voyager",
    "x": 62,
    "z": -6254,
    "originalTimestamp": 1765572221458
  },
  {
    "player": "CaliForLife",
    "rank": "Supporter",
    "x": -14333,
    "z": -4352,
    "originalTimestamp": 1765572221458
  },
  {
    "player": "h0lynaightt",
    "rank": "Explorer",
    "x": -8538,
    "z": 3889,
    "originalTimestamp": 1765572221458
  },
  {
    "player": "xStermin4tore",
    "rank": "Colonist",
    "x": 1732,
    "z": -4886,
    "originalTimestamp": 1765572221458
  },
  {
    "player": "BopBopLittle",
    "rank": "Supporter",
    "x": -6405,
    "z": 2333,
    "originalTimestamp": 1765572221458
  },
  {
    "player": "LongtheBist",
    "rank": "Noble",
    "x": 4993,
    "z": -5332,
    "originalTimestamp": 1765572221458
  },
  {
    "player": "swift",
    "rank": "Archduke",
    "x": 4830,
    "z": 1375,
    "originalTimestamp": 1765572221458
  },
  {
    "player": "LILJITSWIFX",
    "rank": "Supporter",
    "x": 4826,
    "z": 1385,
    "originalTimestamp": 1765572221458
  },
  {
    "player": "Pird_bog",
    "rank": "Colonist",
    "x": -9222,
    "z": -8436,
    "originalTimestamp": 1765572221458
  },
  {
    "player": "flyingdata",
    "rank": "Explorer",
    "x": 7679,
    "z": -4332,
    "originalTimestamp": 1765572221458
  },
  {
    "player": "Fuchs",
    "rank": "Supporter",
    "x": -1202,
    "z": -854,
    "originalTimestamp": 1765572221458
  }
]