[
  {
    "player": "Naytive999",
    "rank": "Member",
    "x": 4603,
    "z": -4134,
    "originalTimestamp": 1767711075405
  },
  {
    "player": "soodspoun",
    "rank": "Viceroy",
    "x": 14204,
    "z": -579,
    "originalTimestamp": 1767711075405
  },
  {
    "player": "xxLeak",
    "rank": "Viceroy",
    "x": -245,
    "z": -5805,
    "originalTimestamp": 1767711075405
  },
  {
    "player": "mhdtarek",
    "rank": "Viceroy",
    "x": 6542,
    "z": -1485,
    "originalTimestamp": 1767711075405
  },
  {
    "player": "Sniperlbaron",
    "rank": "Colonist",
    "x": 17070,
    "z": -7591,
    "originalTimestamp": 1767711075405
  },
  {
    "player": "OGBunlik",
    "rank": "Excelsior",
    "x": -1526,
    "z": -997,
    "originalTimestamp": 1767711075405
  },
  {
    "player": "Illyt",
    "rank": "Explorer",
    "x": -236,
    "z": -6548,
    "originalTimestamp": 1767711075405
  },
  {
    "player": "Geo",
    "rank": "Duke",
    "x": -244,
    "z": -6551,
    "originalTimestamp": 1767711075405
  },
  {
    "player": "yeegeglear",
    "rank": "Supporter",
    "x": 15804,
    "z": 851,
    "originalTimestamp": 1767711075405
  },
  {
    "player": "VenomAugustussy",
    "rank": "Duke",
    "x": 12934,
    "z": -6557,
    "originalTimestamp": 1767711075405
  },
  {
    "player": "clear",
    "rank": "Supporter",
    "x": 13768,
    "z": 2941,
    "originalTimestamp": 1767711075405
  },
  {
    "player": "Alien",
    "rank": "Duke",
    "x": -9653,
    "z": 712,
    "originalTimestamp": 1767711075405
  },
  {
    "player": "zuma88",
    "rank": "Viceroy",
    "x": 13765,
    "z": 153,
    "originalTimestamp": 1767711075405
  },
  {
    "player": "MohammedAep",
    "rank": "Voyager",
    "x": 4647,
    "z": -4106,
    "originalTimestamp": 1767711075405
  },
  {
    "player": "Adrian_Anderas",
    "rank": "Member",
    "x": 4179,
    "z": -5538,
    "originalTimestamp": 1767711075405
  },
  {
    "player": "o_v_0",
    "rank": "Colonist",
    "x": -5262,
    "z": -7276,
    "originalTimestamp": 1767711075405
  },
  {
    "player": "Weronz",
    "rank": "Explorer",
    "x": 4644,
    "z": -4103,
    "originalTimestamp": 1767711075405
  },
  {
    "player": "Daspongeyboi7838",
    "rank": "Member",
    "x": 14673,
    "z": -3447,
    "originalTimestamp": 1767711075405
  },
  {
    "player": "Wennd",
    "rank": "Member",
    "x": 5790,
    "z": -7662,
    "originalTimestamp": 1767711075405
  },
  {
    "player": "TheCrazyIrishGuy",
    "rank": "Colonist",
    "x": -1661,
    "z": -7853,
    "originalTimestamp": 1767711075405
  }
]