[
  {
    "player": "JDanielsito",
    "rank": "Colonist",
    "x": -8671,
    "z": 4341,
    "originalTimestamp": 1765834842869
  },
  {
    "player": "teuli",
    "rank": "Explorer",
    "x": -2696,
    "z": -7738,
    "originalTimestamp": 1765834842869
  },
  {
    "player": "Gawkan",
    "rank": "Noble",
    "x": 17118,
    "z": -7142,
    "originalTimestamp": 1765834842869
  },
  {
    "player": "JustAA_0",
    "rank": "Member",
    "x": -5012,
    "z": 382,
    "originalTimestamp": 1765834842869
  },
  {
    "player": "JaminoCraft",
    "rank": "Explorer",
    "x": 6178,
    "z": -5373,
    "originalTimestamp": 1765834842869
  },
  {
    "player": "BORourke90",
    "rank": "Explorer",
    "x": 6190,
    "z": -5374,
    "originalTimestamp": 1765834842869
  },
  {
    "player": "deathtoworlds",
    "rank": "Member",
    "x": 16731,
    "z": 2198,
    "originalTimestamp": 1765834842869
  },
  {
    "player": "BritishAteriko",
    "rank": "Supporter",
    "x": 59,
    "z": -6278,
    "originalTimestamp": 1765834842869
  },
  {
    "player": "XxIceGinoponzxX",
    "rank": "Member",
    "x": 1646,
    "z": -4887,
    "originalTimestamp": 1765834842869
  },
  {
    "player": "Remiculus",
    "rank": "Conquistador",
    "x": 10515,
    "z": -2757,
    "originalTimestamp": 1765834842869
  },
  {
    "player": "SharkyTheSnowman",
    "rank": "Supporter",
    "x": -4702,
    "z": 379,
    "originalTimestamp": 1765834842869
  },
  {
    "player": "Makuferis",
    "rank": "Supporter",
    "x": -9267,
    "z": -321,
    "originalTimestamp": 1765834842869
  },
  {
    "player": "Marivelle",
    "rank": "Duke",
    "x": 16535,
    "z": 1964,
    "originalTimestamp": 1765834842869
  },
  {
    "player": "Kero_Ioann",
    "rank": "Member",
    "x": 4509,
    "z": -980,
    "originalTimestamp": 1765834842869
  },
  {
    "player": "Sylenciooo",
    "rank": "Excelsior",
    "x": -4637,
    "z": 1733,
    "originalTimestamp": 1765834842869
  },
  {
    "player": "Notorious01",
    "rank": "Member",
    "x": 4094,
    "z": -3717,
    "originalTimestamp": 1765834842869
  },
  {
    "player": "Hans33749",
    "rank": "Colonist",
    "x": 12992,
    "z": -1325,
    "originalTimestamp": 1765834842869
  },
  {
    "player": "Japamagaming",
    "rank": "Explorer",
    "x": 4509,
    "z": -968,
    "originalTimestamp": 1765834842869
  },
  {
    "player": "flyingdata",
    "rank": "Explorer",
    "x": 8685,
    "z": -3099,
    "originalTimestamp": 1765834842869
  },
  {
    "player": "Davifrancis",
    "rank": "Helper",
    "x": -9269,
    "z": -420,
    "originalTimestamp": 1765834842869
  },
  {
    "player": "djmaximovich",
    "rank": "Duke",
    "x": 2518,
    "z": -5395,
    "originalTimestamp": 1765834842869
  },
  {
    "player": "Aeryrion",
    "rank": "Member",
    "x": -5546,
    "z": -7304,
    "originalTimestamp": 1765834842869
  },
  {
    "player": "Zyshia",
    "rank": "Excelsior",
    "x": -1474,
    "z": -1128,
    "originalTimestamp": 1765834842869
  },
  {
    "player": "_HamJam",
    "rank": "Excelsior",
    "x": -9050,
    "z": -2396,
    "originalTimestamp": 1765834842869
  },
  {
    "player": "Heers66",
    "rank": "Viceroy",
    "x": -1836,
    "z": -1621,
    "originalTimestamp": 1765834842869
  },
  {
    "player": "Zeppe",
    "rank": "Supporter",
    "x": -14340,
    "z": -4336,
    "originalTimestamp": 1765834842869
  },
  {
    "player": "Psycho_Luke_",
    "rank": "Duke",
    "x": 10011,
    "z": -2147,
    "originalTimestamp": 1765834842869
  },
  {
    "player": "tuve",
    "rank": "Supporter",
    "x": 2521,
    "z": -329,
    "originalTimestamp": 1765834842869
  }
]