[
  {
    "player": "RUSSIANPENGU",
    "rank": "Duke",
    "x": 6260,
    "z": -3397,
    "originalTimestamp": 1767383094772
  },
  {
    "player": "Forase",
    "rank": "Voyager",
    "x": 985,
    "z": -5931,
    "originalTimestamp": 1767383094772
  },
  {
    "player": "Freyr",
    "rank": "Archduke",
    "x": -6902,
    "z": -5933,
    "originalTimestamp": 1767383094772
  },
  {
    "player": "Gawkan",
    "rank": "Viceroy",
    "x": 16859,
    "z": -7161,
    "originalTimestamp": 1767383094772
  },
  {
    "player": "ivan_poiUA",
    "rank": "Member",
    "x": 3920,
    "z": 320,
    "originalTimestamp": 1767383094772
  },
  {
    "player": "OceanicBlue",
    "rank": "Excelsior",
    "x": 15656,
    "z": 3743,
    "originalTimestamp": 1767383094772
  },
  {
    "player": "Sniperlbaron",
    "rank": "Colonist",
    "x": 16961,
    "z": -7694,
    "originalTimestamp": 1767383094772
  },
  {
    "player": "Mey45",
    "rank": "Voyager",
    "x": 5768,
    "z": 2624,
    "originalTimestamp": 1767383094772
  },
  {
    "player": "UndeadFungi",
    "rank": "Excelsior",
    "x": 14759,
    "z": -6154,
    "originalTimestamp": 1767383094772
  },
  {
    "player": "hidantopchic032",
    "rank": "Member",
    "x": 3927,
    "z": 321,
    "originalTimestamp": 1767383094772
  },
  {
    "player": "FaceyZino",
    "rank": "Duke",
    "x": 17128,
    "z": 986,
    "originalTimestamp": 1767383094772
  },
  {
    "player": "SheepMannieALQ",
    "rank": "Viceroy",
    "x": -9754,
    "z": -5197,
    "originalTimestamp": 1767383094772
  },
  {
    "player": "Rehent_",
    "rank": "Member",
    "x": 3925,
    "z": 329,
    "originalTimestamp": 1767383094772
  },
  {
    "player": "Bluenextcrystal",
    "rank": "Viceroy",
    "x": 12204,
    "z": -8349,
    "originalTimestamp": 1767383094772
  },
  {
    "player": "ruffyduf",
    "rank": "Member",
    "x": -19356,
    "z": -7376,
    "originalTimestamp": 1767383094772
  },
  {
    "player": "VROOMGUYx",
    "rank": "Member",
    "x": -941,
    "z": -4350,
    "originalTimestamp": 1767383094772
  },
  {
    "player": "KingLuckyTiger",
    "rank": "Colonist",
    "x": -8653,
    "z": 1588,
    "originalTimestamp": 1767383094772
  },
  {
    "player": "GhostOfStoodSumo",
    "rank": "Supporter",
    "x": 13530,
    "z": 36,
    "originalTimestamp": 1767383094772
  },
  {
    "player": "Vanaco_Defence_4",
    "rank": "Supporter",
    "x": 2396,
    "z": -109,
    "originalTimestamp": 1767383094772
  },
  {
    "player": "ACE",
    "rank": "Supporter",
    "x": -8821,
    "z": 4868,
    "originalTimestamp": 1767383094772
  },
  {
    "player": "EpicKongoz",
    "rank": "Excelsior",
    "x": -11765,
    "z": -2868,
    "originalTimestamp": 1767383094772
  },
  {
    "player": "Funmasterr",
    "rank": "Viceroy",
    "x": 2614,
    "z": 12,
    "originalTimestamp": 1767383094772
  },
  {
    "player": "The_Gentleman46",
    "rank": "Viceroy",
    "x": 14554,
    "z": 3384,
    "originalTimestamp": 1767383094772
  },
  {
    "player": "OwenIsSoDrippy",
    "rank": "Voyager",
    "x": 13176,
    "z": -2554,
    "originalTimestamp": 1767383094772
  },
  {
    "player": "9bright",
    "rank": "Excelsior",
    "x": 3828,
    "z": -5018,
    "originalTimestamp": 1767383094772
  },
  {
    "player": "BlockWorks123",
    "rank": "Viceroy",
    "x": 1057,
    "z": -5917,
    "originalTimestamp": 1767383094772
  },
  {
    "player": "KOLOKORNEL09",
    "rank": "Member",
    "x": 3241,
    "z": -6140,
    "originalTimestamp": 1767383094772
  },
  {
    "player": "sharkynuu",
    "rank": "Supporter",
    "x": -9292,
    "z": -1026,
    "originalTimestamp": 1767383094772
  },
  {
    "player": "Alexander_0099",
    "rank": "Supporter",
    "x": 14468,
    "z": 1195,
    "originalTimestamp": 1767383094772
  },
  {
    "player": "quickdropnixie",
    "rank": "Supporter",
    "x": 13100,
    "z": -8239,
    "originalTimestamp": 1767383094772
  },
  {
    "player": "falconman2135",
    "rank": "Colonist",
    "x": 2175,
    "z": -1,
    "originalTimestamp": 1767383094772
  }
]