[
  {
    "player": "ninehawtt",
    "rank": "Explorer",
    "x": 4216,
    "z": 2760,
    "originalTimestamp": 1767689974510
  },
  {
    "player": "Tzilla888",
    "rank": "Member",
    "x": -14760,
    "z": -4576,
    "originalTimestamp": 1767689974510
  },
  {
    "player": "Naytive999",
    "rank": "Member",
    "x": 4650,
    "z": -4110,
    "originalTimestamp": 1767689974510
  },
  {
    "player": "ACE",
    "rank": "Supporter",
    "x": -9842,
    "z": -1059,
    "originalTimestamp": 1767689974510
  },
  {
    "player": "Sniperlbaron",
    "rank": "Colonist",
    "x": 16942,
    "z": -7615,
    "originalTimestamp": 1767689974510
  }
]