[
  {
    "player": "Sqwidd_",
    "rank": "Conquistador",
    "x": -10179,
    "z": -4769,
    "originalTimestamp": 1769491509746
  },
  {
    "player": "CobraDenis",
    "rank": "Supporter",
    "x": 3867,
    "z": -7129,
    "originalTimestamp": 1769491509746
  },
  {
    "player": "RedChinaEmperor",
    "rank": "Noble",
    "x": -752,
    "z": -5929,
    "originalTimestamp": 1769491509746
  },
  {
    "player": "Renann067",
    "rank": "Viceroy",
    "x": -6528,
    "z": 4073,
    "originalTimestamp": 1769491509746
  }
]