[
  {
    "player": "JeannB_",
    "rank": "Member",
    "x": -8662,
    "z": 4351,
    "originalTimestamp": 1765749426304
  },
  {
    "player": "xStermin4tore",
    "rank": "Colonist",
    "x": 6559,
    "z": -1665,
    "originalTimestamp": 1765749426304
  },
  {
    "player": "SmallTallahasee",
    "rank": "Supporter",
    "x": 2426,
    "z": 3537,
    "originalTimestamp": 1765749426304
  },
  {
    "player": "Marvin",
    "rank": "Excelsior",
    "x": 1200,
    "z": -2906,
    "originalTimestamp": 1765749426304
  },
  {
    "player": "o_v_0",
    "rank": "Colonist",
    "x": -5548,
    "z": -7296,
    "originalTimestamp": 1765749426304
  },
  {
    "player": "Aeryrion",
    "rank": "Member",
    "x": -5540,
    "z": -7303,
    "originalTimestamp": 1765749426304
  },
  {
    "player": "JDanielsito",
    "rank": "Colonist",
    "x": -8662,
    "z": 4326,
    "originalTimestamp": 1765749426304
  },
  {
    "player": "Pird_bog",
    "rank": "Colonist",
    "x": -9218,
    "z": -8444,
    "originalTimestamp": 1765749426304
  },
  {
    "player": "Marivelle",
    "rank": "Duke",
    "x": 16376,
    "z": 1973,
    "originalTimestamp": 1765749426304
  },
  {
    "player": "Dvrk_Dvce",
    "rank": "Colonist",
    "x": 13594,
    "z": -4485,
    "originalTimestamp": 1765749426304
  },
  {
    "player": "Ikaria_Locktia",
    "rank": "Supporter",
    "x": 7941,
    "z": -5467,
    "originalTimestamp": 1765749426304
  },
  {
    "player": "szepess",
    "rank": "Colonist",
    "x": 12455,
    "z": -9500,
    "originalTimestamp": 1765749426304
  },
  {
    "player": "bob_jake_ish",
    "rank": "Noble",
    "x": -6122,
    "z": 2509,
    "originalTimestamp": 1765749426304
  },
  {
    "player": "FunniJetMan",
    "rank": "Colonist",
    "x": 4352,
    "z": -3845,
    "originalTimestamp": 1765749426304
  },
  {
    "player": "tuve",
    "rank": "Supporter",
    "x": 1756,
    "z": -3840,
    "originalTimestamp": 1765749426304
  },
  {
    "player": "josgbr",
    "rank": "Archduke",
    "x": 7325,
    "z": -6389,
    "originalTimestamp": 1765749426304
  },
  {
    "player": "kinsukghoshXD",
    "rank": "Noble",
    "x": 16395,
    "z": 1986,
    "originalTimestamp": 1765749426304
  },
  {
    "player": "RUSSIANLION",
    "rank": "Excelsior",
    "x": 4846,
    "z": -3831,
    "originalTimestamp": 1765749426304
  },
  {
    "player": "ImperialVisor",
    "rank": "Colonist",
    "x": 7072,
    "z": -3283,
    "originalTimestamp": 1765749426304
  },
  {
    "player": "orangfishe",
    "rank": "Colonist",
    "x": -14483,
    "z": -4461,
    "originalTimestamp": 1765749426304
  },
  {
    "player": "SuperKitty_",
    "rank": "Explorer",
    "x": -6115,
    "z": 2520,
    "originalTimestamp": 1765749426304
  },
  {
    "player": "CrazyKirbby",
    "rank": "Explorer",
    "x": 7334,
    "z": -3048,
    "originalTimestamp": 1765749426304
  },
  {
    "player": "teuli",
    "rank": "Explorer",
    "x": -2694,
    "z": -7738,
    "originalTimestamp": 1765749426304
  },
  {
    "player": "starstruckfate",
    "rank": "Viceroy",
    "x": 16380,
    "z": 1972,
    "originalTimestamp": 1765749426304
  },
  {
    "player": "Generales",
    "rank": "Excelsior",
    "x": 4199,
    "z": -3782,
    "originalTimestamp": 1765749426304
  },
  {
    "player": "z_euos",
    "rank": "Viceroy",
    "x": 6525,
    "z": -3630,
    "originalTimestamp": 1765749426304
  },
  {
    "player": "BORourke90",
    "rank": "Explorer",
    "x": 6282,
    "z": -5379,
    "originalTimestamp": 1765749426304
  }
]