[
  {
    "player": "Telurian_Squnchi",
    "rank": "Excelsior",
    "x": -7725,
    "z": -811,
    "originalTimestamp": 1768837523908
  },
  {
    "player": "Sniperlbaron",
    "rank": "Conquistador",
    "x": 16934,
    "z": -7613,
    "originalTimestamp": 1768837523908
  },
  {
    "player": "falcon5463",
    "rank": "Conquistador",
    "x": -13908,
    "z": -8273,
    "originalTimestamp": 1768837523908
  },
  {
    "player": "Ace_Kit",
    "rank": "Voyager",
    "x": 10523,
    "z": -2766,
    "originalTimestamp": 1768837523908
  },
  {
    "player": "LongtheBist",
    "rank": "Viceroy",
    "x": 4764,
    "z": -5298,
    "originalTimestamp": 1768837523908
  },
  {
    "player": "Stepan01",
    "rank": "Voyager",
    "x": 7047,
    "z": -2438,
    "originalTimestamp": 1768837523908
  },
  {
    "player": "MoonGhost44",
    "rank": "Member",
    "x": 4967,
    "z": -5321,
    "originalTimestamp": 1768837523908
  },
  {
    "player": "NK_Grimm",
    "rank": "Voyager",
    "x": -7032,
    "z": -5905,
    "originalTimestamp": 1768837523908
  },
  {
    "player": "kinsukghoshXD",
    "rank": "Noble",
    "x": 17862,
    "z": 4514,
    "originalTimestamp": 1768837523908
  },
  {
    "player": "eblovich",
    "rank": "Colonist",
    "x": 16989,
    "z": -6295,
    "originalTimestamp": 1768837523908
  },
  {
    "player": "FPSMaster157885",
    "rank": "Member",
    "x": 8355,
    "z": 5943,
    "originalTimestamp": 1768837523908
  },
  {
    "player": "NyaaaImNixie",
    "rank": "Supporter",
    "x": 13296,
    "z": -8118,
    "originalTimestamp": 1768837523908
  },
  {
    "player": "warror230",
    "rank": "Duke",
    "x": 108,
    "z": -2525,
    "originalTimestamp": 1768837523908
  },
  {
    "player": "maroonspinodino",
    "rank": "Voyager",
    "x": -10097,
    "z": -5615,
    "originalTimestamp": 1768837523908
  },
  {
    "player": "Buff_Danny",
    "rank": "Excelsior",
    "x": 5915,
    "z": 1479,
    "originalTimestamp": 1768837523908
  },
  {
    "player": "SometimesTia",
    "rank": "Supporter",
    "x": 4756,
    "z": -8003,
    "originalTimestamp": 1768837523908
  },
  {
    "player": "DarthDilly",
    "rank": "Member",
    "x": -19381,
    "z": -6627,
    "originalTimestamp": 1768837523908
  },
  {
    "player": "Jc499",
    "rank": "Conquistador",
    "x": -8786,
    "z": 5068,
    "originalTimestamp": 1768837523908
  },
  {
    "player": "MrCombat",
    "rank": "Viceroy",
    "x": -4924,
    "z": 2085,
    "originalTimestamp": 1768837523908
  },
  {
    "player": "Heavenly",
    "rank": "Excelsior",
    "x": -309,
    "z": -5004,
    "originalTimestamp": 1768837523908
  },
  {
    "player": "xXClipperXx",
    "rank": "Explorer",
    "x": 4757,
    "z": -5295,
    "originalTimestamp": 1768837523908
  },
  {
    "player": "kropotkin1874",
    "rank": "Explorer",
    "x": 5498,
    "z": -7961,
    "originalTimestamp": 1768837523908
  }
]