[
  {
    "player": "Sindakil",
    "rank": "Colonist",
    "x": -8151,
    "z": 4626,
    "originalTimestamp": 1766091555904
  },
  {
    "player": "Jestorius",
    "rank": "Colonist",
    "x": 16897,
    "z": -7100,
    "originalTimestamp": 1766091555904
  },
  {
    "player": "KOVzinzi",
    "rank": "Supporter",
    "x": 13817,
    "z": -4383,
    "originalTimestamp": 1766091555904
  },
  {
    "player": "Gawkan",
    "rank": "Noble",
    "x": 16888,
    "z": -7230,
    "originalTimestamp": 1766091555904
  },
  {
    "player": "PigyLord",
    "rank": "Excelsior",
    "x": 3315,
    "z": -6014,
    "originalTimestamp": 1766091555904
  },
  {
    "player": "Sad_Zigzag",
    "rank": "Viceroy",
    "x": -18662,
    "z": -2330,
    "originalTimestamp": 1766091555904
  },
  {
    "player": "Makuferis",
    "rank": "Supporter",
    "x": -9122,
    "z": 43,
    "originalTimestamp": 1766091555904
  },
  {
    "player": "Foxfire3321",
    "rank": "Noble",
    "x": -10046,
    "z": -5630,
    "originalTimestamp": 1766091555904
  },
  {
    "player": "KOVsaumya",
    "rank": "Supporter",
    "x": 7394,
    "z": -7300,
    "originalTimestamp": 1766091555904
  },
  {
    "player": "kingads2004",
    "rank": "Colonist",
    "x": -6230,
    "z": -7797,
    "originalTimestamp": 1766091555904
  },
  {
    "player": "Marivelle",
    "rank": "Duke",
    "x": 16593,
    "z": 2027,
    "originalTimestamp": 1766091555904
  },
  {
    "player": "Keav",
    "rank": "Archduke",
    "x": -10044,
    "z": -5628,
    "originalTimestamp": 1766091555904
  },
  {
    "player": "Willow_626",
    "rank": "Member",
    "x": 16690,
    "z": 2050,
    "originalTimestamp": 1766091555904
  },
  {
    "player": "BGamer1704",
    "rank": "Colonist",
    "x": 438,
    "z": -5999,
    "originalTimestamp": 1766091555904
  },
  {
    "player": "TNTistheplace4me",
    "rank": "Viceroy",
    "x": -15247,
    "z": -6054,
    "originalTimestamp": 1766091555904
  },
  {
    "player": "oceanickinsuk",
    "rank": "Voter",
    "x": 16685,
    "z": 2141,
    "originalTimestamp": 1766091555904
  },
  {
    "player": "KCCthePotat0",
    "rank": "Voyager",
    "x": 12251,
    "z": -8653,
    "originalTimestamp": 1766091555904
  },
  {
    "player": "Culph",
    "rank": "Noble",
    "x": -8532,
    "z": -2600,
    "originalTimestamp": 1766091555904
  },
  {
    "player": "Teddy1893",
    "rank": "Member",
    "x": -14610,
    "z": -4723,
    "originalTimestamp": 1766091555904
  },
  {
    "player": "HeedlessComb97",
    "rank": "Explorer",
    "x": 1029,
    "z": -7057,
    "originalTimestamp": 1766091555904
  },
  {
    "player": "TheCrazyIrishGuy",
    "rank": "Explorer",
    "x": -2087,
    "z": -7919,
    "originalTimestamp": 1766091555904
  },
  {
    "player": "GsoTheSnowwoman",
    "rank": "Supporter",
    "x": 15713,
    "z": 1384,
    "originalTimestamp": 1766091555904
  },
  {
    "player": "Davifrancis",
    "rank": "Helper",
    "x": 16137,
    "z": 1627,
    "originalTimestamp": 1766091555904
  },
  {
    "player": "djmaximovich",
    "rank": "Duke",
    "x": 2318,
    "z": -5362,
    "originalTimestamp": 1766091555904
  },
  {
    "player": "VisualParsley38",
    "rank": "Conquistador",
    "x": -15693,
    "z": -6501,
    "originalTimestamp": 1766091555904
  },
  {
    "player": "TurtleTime82",
    "rank": "Member",
    "x": -4952,
    "z": -8620,
    "originalTimestamp": 1766091555904
  },
  {
    "player": "SonnySeven76",
    "rank": "Explorer",
    "x": -14352,
    "z": -4404,
    "originalTimestamp": 1766091555904
  },
  {
    "player": "raptor355",
    "rank": "Excelsior",
    "x": 1777,
    "z": -4467,
    "originalTimestamp": 1766091555904
  },
  {
    "player": "OGTorta",
    "rank": "Excelsior",
    "x": -1786,
    "z": -2749,
    "originalTimestamp": 1766091555904
  },
  {
    "player": "Xyrothic",
    "rank": "Conquistador",
    "x": 13675,
    "z": 3024,
    "originalTimestamp": 1766091555904
  },
  {
    "player": "Marvin",
    "rank": "Excelsior",
    "x": 2937,
    "z": -4207,
    "originalTimestamp": 1766091555904
  },
  {
    "player": "Mr_Specter",
    "rank": "Excelsior",
    "x": 2972,
    "z": -4168,
    "originalTimestamp": 1766091555904
  },
  {
    "player": "Hayden747",
    "rank": "Viceroy",
    "x": -10529,
    "z": -6494,
    "originalTimestamp": 1766091555904
  },
  {
    "player": "JustAA_0",
    "rank": "Member",
    "x": -4975,
    "z": 384,
    "originalTimestamp": 1766091555904
  }
]