[
  {
    "player": "Radioactive661",
    "rank": "Voyager",
    "x": 17106,
    "z": -8248,
    "originalTimestamp": 1769540897817
  },
  {
    "player": "squeaky_possum",
    "rank": "Conquistador",
    "x": 4604,
    "z": -6949,
    "originalTimestamp": 1769540897817
  },
  {
    "player": "Delotris",
    "rank": "Supporter",
    "x": -2518,
    "z": -9298,
    "originalTimestamp": 1769540897817
  },
  {
    "player": "Davi",
    "rank": "Helper",
    "x": -15535,
    "z": -7967,
    "originalTimestamp": 1769540897817
  },
  {
    "player": "AlchakSigma",
    "rank": "Duke",
    "x": 2000,
    "z": -5364,
    "originalTimestamp": 1769540897817
  },
  {
    "player": "SIBDestroyer",
    "rank": "Supporter",
    "x": 11019,
    "z": -4001,
    "originalTimestamp": 1769540897817
  },
  {
    "player": "ivan_poiUA",
    "rank": "Explorer",
    "x": 3810,
    "z": 366,
    "originalTimestamp": 1769540897817
  },
  {
    "player": "deathtoworlds",
    "rank": "Colonist",
    "x": 20273,
    "z": 5523,
    "originalTimestamp": 1769540897817
  },
  {
    "player": "mutedgsouxi",
    "rank": "Supporter",
    "x": 13289,
    "z": 280,
    "originalTimestamp": 1769540897817
  },
  {
    "player": "Yaros_Jarro",
    "rank": "Member",
    "x": 3802,
    "z": 370,
    "originalTimestamp": 1769540897817
  },
  {
    "player": "XxIceGinoponzxX",
    "rank": "Member",
    "x": 5701,
    "z": -670,
    "originalTimestamp": 1769540897817
  },
  {
    "player": "sleaps",
    "rank": "Conquistador",
    "x": 13280,
    "z": 295,
    "originalTimestamp": 1769540897817
  },
  {
    "player": "Yeat",
    "rank": "Duke",
    "x": 5728,
    "z": 2632,
    "originalTimestamp": 1769540897817
  },
  {
    "player": "Fraancis",
    "rank": "Excelsior",
    "x": -8338,
    "z": 941,
    "originalTimestamp": 1769540897817
  },
  {
    "player": "OH3L4",
    "rank": "Colonist",
    "x": 8429,
    "z": 5922,
    "originalTimestamp": 1769540897817
  },
  {
    "player": "itechniker",
    "rank": "Colonist",
    "x": 16935,
    "z": -7568,
    "originalTimestamp": 1769540897817
  },
  {
    "player": "BGamer1704",
    "rank": "Conquistador",
    "x": 903,
    "z": -5912,
    "originalTimestamp": 1769540897817
  },
  {
    "player": "definitelynotFAX",
    "rank": "Member",
    "x": -5316,
    "z": -8547,
    "originalTimestamp": 1769540897817
  },
  {
    "player": "IXXXXXXI",
    "rank": "Voyager",
    "x": 5704,
    "z": -686,
    "originalTimestamp": 1769540897817
  },
  {
    "player": "Jaybari",
    "rank": "Explorer",
    "x": 20831,
    "z": 4226,
    "originalTimestamp": 1769540897817
  },
  {
    "player": "ARMADILLO_90",
    "rank": "Explorer",
    "x": 7374,
    "z": -3045,
    "originalTimestamp": 1769540897817
  },
  {
    "player": "SchruteFarms327",
    "rank": "Viceroy",
    "x": 7132,
    "z": -3344,
    "originalTimestamp": 1769540897817
  }
]