[
  {
    "player": "squeaky_possum",
    "rank": "Conquistador",
    "x": 4604,
    "z": -6949,
    "originalTimestamp": 1769570787679
  },
  {
    "player": "OrigamiWawa",
    "rank": "Voter",
    "x": 11357,
    "z": -9671,
    "originalTimestamp": 1769570787679
  },
  {
    "player": "FirstLeak",
    "rank": "Supporter",
    "x": 2498,
    "z": 971,
    "originalTimestamp": 1769570787679
  },
  {
    "player": "AlchakSigma",
    "rank": "Duke",
    "x": 6700,
    "z": -4677,
    "originalTimestamp": 1769570787679
  },
  {
    "player": "J0k9r",
    "rank": "Colonist",
    "x": 7497,
    "z": -3044,
    "originalTimestamp": 1769570787679
  },
  {
    "player": "HonkDooder",
    "rank": "Voyager",
    "x": -12073,
    "z": -2200,
    "originalTimestamp": 1769570787679
  },
  {
    "player": "Itz_iber",
    "rank": "Explorer",
    "x": -9959,
    "z": -5149,
    "originalTimestamp": 1769570787679
  },
  {
    "player": "Citereh099",
    "rank": "Viceroy",
    "x": 6896,
    "z": -3797,
    "originalTimestamp": 1769570787679
  },
  {
    "player": "_Real_Lucid_",
    "rank": "Member",
    "x": -9959,
    "z": -5157,
    "originalTimestamp": 1769570787679
  },
  {
    "player": "OGConcord4Life",
    "rank": "Supporter",
    "x": -14077,
    "z": -3971,
    "originalTimestamp": 1769570787679
  },
  {
    "player": "Mashad",
    "rank": "Helper",
    "x": -288,
    "z": -6371,
    "originalTimestamp": 1769570787679
  },
  {
    "player": "Aerneas",
    "rank": "Duke",
    "x": -5961,
    "z": 2090,
    "originalTimestamp": 1769570787679
  },
  {
    "player": "Tixgow",
    "rank": "Voyager",
    "x": -8891,
    "z": -3562,
    "originalTimestamp": 1769570787679
  },
  {
    "player": "America",
    "rank": "Archduke",
    "x": -11349,
    "z": -3923,
    "originalTimestamp": 1769570787679
  }
]