[
  {
    "player": "DiscoPotato",
    "rank": "Supporter",
    "x": -14807,
    "z": -5487,
    "originalTimestamp": 1769325457832
  },
  {
    "player": "NyaaaImNixie",
    "rank": "Supporter",
    "x": 13027,
    "z": -8229,
    "originalTimestamp": 1769325457832
  },
  {
    "player": "chigglesYT",
    "rank": "Conquistador",
    "x": -19344,
    "z": -7302,
    "originalTimestamp": 1769325457832
  },
  {
    "player": "iamnoob963",
    "rank": "Voyager",
    "x": 7970,
    "z": -5744,
    "originalTimestamp": 1769325457832
  },
  {
    "player": "HonkDooder",
    "rank": "Voyager",
    "x": -12643,
    "z": -2393,
    "originalTimestamp": 1769325457832
  },
  {
    "player": "LAW4321",
    "rank": "Conquistador",
    "x": -19406,
    "z": -7144,
    "originalTimestamp": 1769325457832
  },
  {
    "player": "Delotris",
    "rank": "Supporter",
    "x": -2451,
    "z": -9386,
    "originalTimestamp": 1769325457832
  },
  {
    "player": "Nayakk",
    "rank": "Explorer",
    "x": 7971,
    "z": -5728,
    "originalTimestamp": 1769325457832
  },
  {
    "player": "jmbj",
    "rank": "Explorer",
    "x": 16291,
    "z": 1800,
    "originalTimestamp": 1769325457832
  }
]